vmi/__init__.py
vmi/_walkpkg.py
vmi/vapp.py
vmi/vask.py
vmi/vath.py
vmi/vcc.py
vmi/vcg.py
vmi/vickle.py
vmi/vicom.py
vmi/view.py
vmi/vimage.py
vmi/vord.py
vmi/vpoly.py
vmi/vprop.py
vmi/vproptool.py
vmi/vrc.py
vmi/application/Bone_Meal&Implants_Measure.py
vmi/application/Cup_marker.py
vmi/application/HiHip_docx.py
vmi/application/KidneyImageRegistration.py
vmi/application/PSI_THA_AI.py
vmi/application/PSI_THA_Web.py
vmi/application/Pelvic_mark.py
vmi/application/Propsi_HTO.py
vmi/application/Propsi_TH.py
vmi/application/StraightMan.py
vmi/application/__init__.py
vmi/application/acetabular_segment.py
vmi/application/blood_vessel.py
vmi/application/brain.py
vmi/application/brain_1.0.py
vmi/application/cage.py
vmi/application/dicom_to_series.py
vmi/application/dicom_uploader.py
vmi/application/image_to_stl.py
vmi/application/pelvis_mark_detection.py
vmi/application/skydio.py
vmi/application/skyward.py
vmi/application/tutorials.py
vmi/example/__init__.py
vmi/example/design_guide_plate.py
vmi/example/image_edit_path.py
vmi/example/image_reslice.py
vmi/example/interaction_box.py
vmi/example/pick_make_curve.py
vmi/example/read_dicom_slice_view.py
vmi/example/surface_volume_rendering.py
vmi-0.6.15.dist-info/LICENSE
vmi-0.6.15.dist-info/METADATA
vmi-0.6.15.dist-info/WHEEL
vmi-0.6.15.dist-info/top_level.txt
vmi-0.6.15.dist-info/RECORD
