Metadata-Version: 2.1
Name: vmi
Version: 0.6.15
Summary: Visual Medical Innovation powered by WANGYiping
Home-page: http://www.med-3d.top:1111/f/e386e5d3c12f4aaeb523/
Author: sjtu_6547
Author-email: 88172828@qq.com
License: UNKNOWN
Keywords: Qt PySide2 SimpleITK itk vtk pythonocc-core OpenCASCADE CGAL
Platform: UNKNOWN
Classifier: Development Status :: 2 - Pre-Alpha
Classifier: Environment :: Win32 (MS Windows)
Classifier: Intended Audience :: Developers
Classifier: License :: OSI Approved :: GNU General Public License v3 or later (GPLv3+)
Classifier: Operating System :: OS Independent
Classifier: Programming Language :: Python :: 3.7
Classifier: Topic :: Multimedia :: Graphics :: 3D Modeling
Classifier: Topic :: Multimedia :: Graphics :: 3D Rendering
Classifier: Topic :: Scientific/Engineering :: Medical Science Apps.
Classifier: Topic :: Scientific/Engineering :: Visualization
Requires-Python: >=3.6
Requires-Dist: PySide2 (>=5.14)
Requires-Dist: SimpleITK (>=1.2)
Requires-Dist: vtk (>=8.1)
Requires-Dist: pydicom (>=1.4)
Requires-Dist: numba (>=0.48)
Requires-Dist: numpy (>=1.18)
Requires-Dist: scipy (>=1.4)
Requires-Dist: lz4 (>=3.0)
